doctrine/__init__.py
doctrine/_version.py
doctrine/py.typed
doctrine-0.6.0.dist-info/METADATA
doctrine-0.6.0.dist-info/WHEEL
doctrine-0.6.0.dist-info/top_level.txt
doctrine-0.6.0.dist-info/RECORD
