Metadata-Version: 2.1
Name: doctrine
Version: 0.6.0
Summary: UNKNOWN
Home-page: https://github.com/avengerpenguin/doctrine
Author: Ross Fenning
Author-email: github@rossfenning.co.uk
License: UNKNOWN
Platform: UNKNOWN
Requires-Dist: invoke
Provides-Extra: test
Requires-Dist: pytest ; extra == 'test'
Requires-Dist: pytest-watch ; extra == 'test'
Requires-Dist: pytest-pikachu ; extra == 'test'
Requires-Dist: pytest-mypy ; extra == 'test'
